{
    "fishes": [
        {
            "id": 1,
            "name": "Скалярия",
            "image": "../images/Angelfish.jpg",
            "description": "Элегантные пресноводные рыбы с треугольными плавниками. Популярны в аквариумистике благодаря красивому внешнему виду.",
            "features": [
                "Высокое плоское тело",
                "Миролюбивый характер",
                "Чувствительны к качеству воды"
            ],
            "lifespan": "8-10 лет"
        },
        {
            "id": 2,
            "name": "Золотая рыбка",
            "image": "../images/Goldfish.webp",
            "description": "Одна из самых известных аквариумных рыб. Существует множество разновидностей с разной формой тела и окраской.",
            "features": [
                "Выносливость",
                "Всеядность",
                "Яркая окраска"
            ],
            "lifespan": "10-15 лет"
        },
        {
            "id": 3,
            "name": "Гуппи",
            "image": "../images/Guppy.webp",
            "description": "Маленькие живородящие рыбки с яркой окраской. Идеальны для начинающих аквариумистов.",
            "features": [
                "Простота в содержании",
                "Яркие самцы",
                "Быстро размножаются"
            ],
            "lifespan": "2-3 года"
        },
        {
            "id": 4,
            "name": "Петушок (Бойцовая рыбка)",
            "image": "../images/BettaFish.webp",
            "description": "Известны своей красивой вуалевой формой плавников и агрессивным поведением к сородичам.",
            "features": [
                "Яркая окраска",
                "Агрессия к себе подобным",
                "Могут дышать атмосферным воздухом"
            ],
            "lifespan": "3-5 лет"
        },
        {
            "id": 5,
            "name": "Неон",
            "image": "../images/NeonTetra.webp",
            "description": "Маленькие стайные рыбки с яркой светящейся полосой. Создают эффектное зрелище в аквариуме.",
            "features": [
                "Стайное поведение",
                "Яркая голубая полоса",
                "Мирный нрав"
            ],
            "lifespan": "5-8 лет"
        }
    ]
}